{"id": "43e535de-a804-440d-b323-8ee35d2030f4", "type": "commit-range", "scans": [{"id": "6a1a3af5820ddb7127fc09805a098c7ec4a44fb0", "type": "commit", "entities_with_incidents": [{"mode": "NEW", "filename": ".gitattributes", "incidents": [], "total_incidents": 0, "total_occurrences": 0}, {"mode": "NEW", "filename": ".gitignore", "incidents": [], "total_incidents": 0, "total_occurrences": 0}, {"mode": "NEW", "filename": "README.md", "incidents": [], "total_incidents": 0, "total_occurrences": 0}, {"mode": "NEW", "filename": "kitti/2011_09_26_drive_0005_sync/0-frame.json", "incidents": [], "total_incidents": 0, "total_occurrences": 0}, {"mode": "NEW", "filename": "nutonomy/scene-0006/0-frame.json", "incidents": [], "total_incidents": 0, "total_occurrences": 0}], "extra_info": {"author": "Xintong Xia", "email": "xintong@uber.com", "date": "Fri Feb 22 08:32:57 2019 +0100"}, "total_incidents": 0, "total_occurrences": 0}], "total_incidents": 0, "total_occurrences": 0, "secrets_engine_version": "2.140.0"}
